hello251114/__init__.py
hello251114/main.py
hello251114-0.1.1.dist-info/METADATA
hello251114-0.1.1.dist-info/WHEEL
hello251114-0.1.1.dist-info/entry_points.txt
hello251114-0.1.1.dist-info/licenses/LICENSE
hello251114-0.1.1.dist-info/RECORD
